app_json_file_cache/__init__.py
app_json_file_cache/app_cache.py
app_json_file_cache/data_cache.py
app_json_file_cache/function_cache.py
app_json_file_cache/test_basics.py
app_json_file_cache/test_default_function.py
app_json_file_cache-1.0.1.dist-info/LICENSE
app_json_file_cache-1.0.1.dist-info/METADATA
app_json_file_cache-1.0.1.dist-info/WHEEL
app_json_file_cache-1.0.1.dist-info/top_level.txt
app_json_file_cache-1.0.1.dist-info/RECORD
