Metadata-Version: 2.2
Name: app_json_file_cache
Version: 1.0.1
Summary: Simple JSON cache for expensive functions, respecting user directories
Author-email: Johannes Ebke <johannes@ebke.org>
License: MIT
Project-URL: Homepage, https://github.com/JohannesEbke/app_json_file_cache
Project-URL: Repository, https://github.com/JohannesEbke/app_json_file_cache.git
Project-URL: Issues, https://github.com/JohannesEbke/app_json_file_cache/issues
Keywords: xdg,json,cache,function cache,memoization,memoisation
Classifier: Development Status :: 5 - Production/Stable
Classifier: Intended Audience :: Developers
Classifier: Programming Language :: Python :: 3
Classifier: Operating System :: OS Independent
Requires-Python: >=3.7
License-File: LICENSE
Requires-Dist: platformdirs
